DM/DM.sv
module DM(
        input [31:0] Address,
        input [31:0] DataWr,
        input DMWr,
        input [2:0] DMCtrl,
        output reg [31:0] DataRd
    );

    logic [7:0] data_mem [31:0];
    logic [7:0] data1, data2, data3, data4;
    logic [7:0] out1, out2, out3, out4;

    initial begin
        for (int i = 0; i < 32; i++) begin
            data_mem[i] = 8'b0;
        end
    end

    always @(*) begin
       data1 = DataWr[31:24];
       data2 = DataWr[23:16];
       data3 = DataWr[15:8];
       data4 = DataWr[7:0];

        if (DMWr == 1) begin
            case (DMCtrl)
                3'b000 :
                    begin 
                        data_mem[Address] = data4;
                        data_mem[Address + 1] = 8'b0;
                        data_mem[Address + 2] = 8'b0;
                        data_mem[Address + 3] = 8'b0;
                    end
                3'b001 : 
                    begin 
                        data_mem[Address] = data4;
                        data_mem[Address + 1] = data3;
                        data_mem[Address + 2] = 8'b0;
                        data_mem[Address + 3] = 8'b0;
                    end
                3'b010 : 
                    begin
                        data_mem[Address] = data4;
                        data_mem[Address + 1] = data3;
                        data_mem[Address + 2] = data2;
                        data_mem[Address + 3] = data1;
                    end 
            endcase
        end
        else begin 
            case (DMCtrl)
                3'b000 : 
                    begin
                        out4 = data_mem[Address];
                        DataRd = {{24{out4[7]}}, out4};
                    end 
                3'b001:
                    begin
                        out4 = data_mem[Address];
                        out3 = data_mem[Address + 1];
                        DataRd = {{16{out3[7]}}, out3, out4};
                    end 
                3'b010:
                    begin
                        out4 = data_mem[Address];
                        out3 = data_mem[Address + 1];
                        out2 = data_mem[Address + 2];
                        out1 = data_mem[Address + 3];
                        DataRd = {out1, out2, out3, out4};
                    end 
                3'b100 :
                    begin
                        out4 = data_mem[Address];
                        DataRd = {{24{1'b0}}, out4};
                    end 
                3'b101 :
                    begin
                        out4 = data_mem[Address];
                        out3 = data_mem[Address + 1];
                        DataRd = {{16{1'b0}}, out3, out4};
                    end 
            endcase
        end
    end
endmodule

BU/BU.sv
module BU(
        input logic [31:0] A,
        input logic [31:0] B,
        input logic [4:0] BrOp,
        output reg NextPCSrc
    );

    always @(*)
        case(BrOp)
            5'b00000 : NextPCSrc = 0;
            5'b11111 : NextPCSrc = 1;
            5'b01000 : NextPCSrc = (A == B);
            5'b01001 : NextPCSrc = (A != B);
            5'b01100 : NextPCSrc = ($signed(A) < $signed(B));
            5'b01101 : NextPCSrc = ($signed(A) >= $signed(B));
            5'b01110 : NextPCSrc = (A < B);
            5'b01111 : NextPCSrc = (A >= B);

            default NextPCSrc = 0;
        endcase
    
endmodule

ALU/ALU.sv
module ALU(
    input [31:0] A,
    input [31:0] B,
    input [3:0] ALUop,
    output reg [31:0] ALUS
    );

    always @(*)
      
    begin
        case(ALUop)
            4'b0000: ALUS = A + B; // Suma
            4'b1000: ALUS = A - B; // Resta
            4'b0111: ALUS = A & B; // AND
            4'b0110: ALUS = A | B; // OR
            4'b0100: ALUS = A ^ B; // XOR
            4'b0001: ALUS = A << B; // Corrimiento lógico izquierdo.
            4'b0101: ALUS = A >> B; // Corrimiento lógico derecho.
            4'b1101: ALUS = A >>> B; // Corrimiento aritmético a la derecha.
            4'b0010: ALUS = ($signed(A) < $signed(B)); // Menor que B (con signo)
            4'b0011: ALUS = A < B; // Menor que B (sin signo)
            default: ALUS = 32'b0; // Default en caso de ALUop desconocido
        endcase
    end
endmodule

IU/IU.sv
module IU(
    input [24:0] imm,
    input [2:0] src,
    output reg [31:0] ext
);

always @(*) begin
    case(src)
        3'b000: ext = (imm[7:5] == 3'b101 || imm[7:5] == 3'b001) ? {{27{imm[17]}},imm[17:13]} : { {20{imm[24]}}, imm[24:13] }; //Tipo I
        3'b001: ext = {{20{imm[24]}}, imm[24:18], imm[4:0]}; // Tipo S
        3'b101: ext = {{20{imm[24]}}, imm[0], imm[23:18], imm[4:1], 1'b0 }; // Tipo B
        3'b010: ext = {imm[24:5], 12'b0}; // Tipo U
        3'b110: ext = {{12{imm[24]}},imm[12:5], imm[13], imm[23:14], 1'b0}; // Tipo J
    endcase
end

endmodule

RU/RU.sv
module RU (
  input logic clk,
  input logic ruWr,
  input logic [4:0] rs1,
  input logic [4:0] rs2,
  input logic [4:0] rd,
  input logic [31:0] DataWr,
  output logic [31:0] ruRs1,
  output logic [31:0] ruRs2
);

  logic [31:0] registers [0:31];

  initial begin
    for (int i = 0; i < 32; i++) begin
      registers[i] = 0;
    registers[2] = 5'b11111;
    end
  end

  assign ruRs1 = (rs1 == 0) ? 0 : registers[rs1];
  assign ruRs2 = (rs2 == 0) ? 0 : registers[rs2];

  always_ff @(posedge clk) begin
    if ((ruWr == 1) && (rd != 0))
      registers[rd] <= DataWr;
  end

endmodule

CU/CU.sv
module CU(
        input [6:0] Opcode,
        input [2:0] Function3,
        input [6:0] Function7,
        output logic [2:0] ImmSrc = 3'b000,
        output logic ALUASrc = 0,
        output logic ALUBSrc = 0,
        output logic RUWr = 0,
        output logic [4:0] BrOp = 5'b00000,
        output logic [3:0] ALUOp = 4'b0000,
        output logic DMWr = 0,
        output logic [2:0] DMCtrl = 3'b000,
        output logic [1:0] RUDataWrSrc = 2'b00
    );

    always @(*) begin
        case(Opcode)
            7'b0110011: begin //Tipo R
                ImmSrc = 3'b000; 
                BrOp = 5'b00000; 
                DMWr = 1'b0; 
                DMCtrl = 3'b000; 
                RUWr = 1'b1; 
                ALUASrc = 1'b0; 
                ALUBSrc = 1'b0; 
                ALUOp = {Function7[5], Function3[2:0]};
                RUDataWrSrc = 2'b00;    
            end
            7'b0010011: begin //Tipo I
                ImmSrc = 3'b000;
                BrOp = 5'b00000;
                DMWr = 1'b0;
                DMCtrl = 3'b000;
                RUWr = 1'b1; 
                ALUASrc = 1'b0;
                ALUBSrc = 1'b1;
                if (Function3 == 3'b101 || 3'b001) begin
                    ALUOp = {Function7[5], Function3[2:0]};
                end else begin
                    ALUOp = {1'b0,Function3[2:0]};
                end
                RUDataWrSrc = 2'b00;
            end
            7'b1100011: begin //Tipo B
                ImmSrc = 3'b101;  
                BrOp = {2'b01, Function3[2:0]};
                DMWr = 1'b0;
                DMCtrl = 3'b000;
                RUWr = 1'b0;
                ALUASrc = 1'b1;
                ALUBSrc = 1'b1;
                ALUOp = 4'b0000;
                RUDataWrSrc = 2'b00;
            end
            7'b0100011: begin //Tipo S
                ImmSrc = 3'b001;  
                BrOp = 5'b00000;
                DMWr = 1'b1;
                DMCtrl = Function3[2:0];
                RUWr = 1'b0;
                ALUASrc = 1'b0;
                ALUBSrc = 1'b1;
                ALUOp = 4'b0000;
                RUDataWrSrc = 2'b00;
            end 
            7'b0000011: begin //Tipo I - Load
                ImmSrc = 3'b000;  
                BrOp = 5'b00000;
                DMWr = 1'b0;
                DMCtrl = Function3[2:0];
                RUWr = 1'b1;
                ALUASrc = 1'b0;
                ALUBSrc = 1'b1;
                ALUOp = 4'b0000;
                RUDataWrSrc = 2'b01;
            end
            7'b1100111: begin //Tipo I - Jalr
                ImmSrc = 3'b000;  
                BrOp = 5'b11111;
                DMWr = 1'b0;
                DMCtrl = 3'b000;
                RUWr = 1'b0;
                ALUASrc = 1'b0;
                ALUBSrc = 1'b1;
                ALUOp = 4'b0000;
                RUDataWrSrc = 2'b00;
            end  
            7'b1101111: begin //Tipo J
                ImmSrc = 3'b110;  
                BrOp = 5'b11111;
                DMWr = 1'b0;
                DMCtrl = 3'b000;
                RUWr = 1'b1;
                ALUASrc = 1'b1;
                ALUBSrc = 1'b1;
                ALUOp = 4'b0000;
                RUDataWrSrc = 2'b10;
            end 
            7'b0110111: begin //Tipo U - lui
                ImmSrc = 3'b010;  
                BrOp = 5'b00000;
                DMWr = 1'b0;
                DMCtrl = 3'b000;
                RUWr = 1'b1;
                ALUASrc = 1'b0;
                ALUBSrc = 1'b1;
                ALUOp = 4'b0000;
                RUDataWrSrc = 2'b00;
            end 
            7'b0010111: begin //Tipo U - auipc
                ImmSrc = 3'b010;  
                BrOp = 5'b00000;
                DMWr = 1'b0;
                DMCtrl = 3'b000;
                RUWr = 1'b1;
                ALUASrc = 1'b1;
                ALUBSrc = 1'b1;
                ALUOp = 4'b0000;
                RUDataWrSrc = 2'b00;
            end 

        default BrOp = 5'b00000;

        endcase
    end
endmodule

IM/IM.sv
module IM(
    input [31:0] address,
    output reg [31:0] instruction
);

    logic [7:0] ins_mem [0:31];
    reg [7:0] out1, out2, out3, out4;

    initial begin
        $readmemb("IM/instructions.txt", ins_mem);
    end

    always @(*) begin
       out1 = ins_mem[address];
       out2 = ins_mem[address + 1];
       out3 = ins_mem[address + 2];
       out4 = ins_mem[address + 3];
       instruction = {out1, out2, out3, out4};
    end

endmodule

PC/PC.sv
module PC(
    input clk,
    input logic [31:0] PC_in,
    output logic [31:0] PC_out
);

initial begin
    PC_out = 32'b0;
end

always @(posedge clk) begin
    PC_out <= PC_in;
end

endmodule

MuxPC.sv
module MuxPC(
    input reg [31:0] PC_4,
    input reg [31:0] AluJump,
    input logic NextPCSrc, 
    output reg [31:0] NextPC = 32'h00000000 
);

always @* begin
    if (NextPCSrc) begin
        NextPC <= AluJump; 
    end else begin
        NextPC <= PC_4 + 4; 
    end
end

endmodule

monociclo.sv
`include "PC/PC.sv"
`include "IM/IM.sv"
`include "CU/CU.sv"
`include "RU/RU.sv"
`include "IU/IU.sv"
`include "ALU/ALU.sv"
`include "BU/BU.sv"
`include "DM/DM.sv"
`include "MuxPC.sv"

module monociclo(
        input clk
    );

    logic NEXT_PC_SRC; 
    logic [31:0] PC_OUT;
    logic [31:0] INSTRUCTION;
    logic RUWR, ALUASRC, ALUBSRC;
    logic [2:0] IMM_SRC;
    logic [4:0] BR_OP;
    logic [3:0] ALUOP;
    logic DM_WR;
    logic [2:0] DM_CTRL;
    logic [1:0] RUDATA_WR_SRC;
    logic [31:0] ALURES;
    logic [31:0] RU_RS1;
    logic [31:0] RU_RS2;
    logic [31:0] INALUA;
    logic [31:0] INALUB;
    logic [31:0] IMMEXT;
    logic [31:0] RU_DATA_WR;
    logic [31:0] DATA_RD;
    logic [31:0] PC_TEMP;

    MuxPC MuxPC_inst(
        .PC_4(PC_OUT),
        .AluJump(ALURES),
        .NextPCSrc(NEXT_PC_SRC),
        .NextPC(PC_TEMP)
    );

    PC PC_inst (
        .clk(clk),
        .PC_in(PC_TEMP),
        .PC_out(PC_OUT)
    );

    IM IM_inst(
        .address(PC_OUT),
        .instruction(INSTRUCTION)
    );

    CU CU_inst(
        .Opcode(INSTRUCTION[6:0]),
        .Function3(INSTRUCTION[14:12]),
        .Function7(INSTRUCTION[31:25]),
        .ImmSrc(IMM_SRC),
        .ALUASrc(ALUASRC),
        .ALUBSrc(ALUBSRC),
        .RUWr(RUWR),
        .BrOp(BR_OP),
        .ALUOp(ALUOP),
        .DMWr(DM_WR),
        .DMCtrl(DM_CTRL),
        .RUDataWrSrc(RUDATA_WR_SRC)
        );

    RU RU_inst(
        .clk(clk),
        .ruWr(RUWR),
        .rs1(INSTRUCTION[19:15]),
        .rs2(INSTRUCTION [24:20]),
        .rd(INSTRUCTION[11:7]),
        .DataWr(RU_DATA_WR),
        .ruRs1(RU_RS1),
        .ruRs2(RU_RS2)
        );

    IU IU_inst(
        .imm(INSTRUCTION[31:7]),
        .src(IMM_SRC),
        .ext(IMMEXT)
        );

    ALU ALU_inst (
        .A(INALUA),
        .B(INALUB),
        .ALUop(ALUOP),
        .ALUS(ALURES)
        );

    BU BU_inst(
        .A(RU_RS1),
        .B(RU_RS2),
        .BrOp(BR_OP),
        .NextPCSrc(NEXT_PC_SRC)
        );

    DM DM_inst (
        .Address(ALURES),
        .DataWr(RU_RS2),
        .DMWr(DM_WR),
        .DMCtrl(DM_CTRL),
        .DataRd(DATA_RD)
        );

    always @(*) begin
        if (ALUASRC == 1'b1) begin
            INALUA <= PC_OUT; 
        end 
        else begin
            INALUA <= RU_RS1;
        end
        if (ALUBSRC == 1'b1) begin
            INALUB <= IMMEXT;
        end
        else begin
            INALUB <= RU_RS2; 
        end
        case(RUDATA_WR_SRC)
            2'b00: RU_DATA_WR <= ALURES;
            2'b01: RU_DATA_WR <= DATA_RD;
            2'b10: RU_DATA_WR <= PC_TEMP;
        endcase
    end
endmodule

monociclo_tb.sv
module monociclo_tb;
    logic clk_tb;

    monociclo monociclo_inst(
        .clk(clk_tb)
    );

always #5 clk_tb = ~clk_tb;
  
initial begin
    $dumpfile("monociclo_tb.vcd");
    $dumpvars(0, monociclo_tb);

    clk_tb = 1;

    #200 $finish; 
end

endmodule

monociclo_tb.vcd
$date
	Tue Apr 30 00:36:58 2024
$end
$version
	Icarus Verilog
$end
$timescale
	1s
$end
$scope module monociclo_tb $end
$var reg 1 ! clk_tb $end
$scope module monociclo_inst $end
$var wire 1 ! clk $end
$var wire 32 " RU_RS2 [31:0] $end
$var wire 32 # RU_RS1 [31:0] $end
$var wire 1 $ RUWR $end
$var wire 2 % RUDATA_WR_SRC [1:0] $end
$var wire 32 & PC_TEMP [31:0] $end
$var wire 32 ' PC_OUT [31:0] $end
$var wire 1 ( NEXT_PC_SRC $end
$var wire 32 ) INSTRUCTION [31:0] $end
$var wire 3 * IMM_SRC [2:0] $end
$var wire 32 + IMMEXT [31:0] $end
$var wire 1 , DM_WR $end
$var wire 3 - DM_CTRL [2:0] $end
$var wire 32 . DATA_RD [31:0] $end
$var wire 5 / BR_OP [4:0] $end
$var wire 32 0 ALURES [31:0] $end
$var wire 4 1 ALUOP [3:0] $end
$var wire 1 2 ALUBSRC $end
$var wire 1 3 ALUASRC $end
$var reg 32 4 INALUA [31:0] $end
$var reg 32 5 INALUB [31:0] $end
$var reg 32 6 RU_DATA_WR [31:0] $end
$scope module ALU_inst $end
$var wire 32 7 A [31:0] $end
$var wire 32 8 B [31:0] $end
$var wire 4 9 ALUop [3:0] $end
$var reg 32 : ALUS [31:0] $end
$upscope $end
$scope module BU_inst $end
$var wire 5 ; BrOp [4:0] $end
$var wire 32 < B [31:0] $end
$var wire 32 = A [31:0] $end
$var reg 1 ( NextPCSrc $end
$upscope $end
$scope module CU_inst $end
$var wire 3 > Function3 [2:0] $end
$var wire 7 ? Function7 [6:0] $end
$var wire 7 @ Opcode [6:0] $end
$var reg 1 3 ALUASrc $end
$var reg 1 2 ALUBSrc $end
$var reg 4 A ALUOp [3:0] $end
$var reg 5 B BrOp [4:0] $end
$var reg 3 C DMCtrl [2:0] $end
$var reg 1 , DMWr $end
$var reg 3 D ImmSrc [2:0] $end
$var reg 2 E RUDataWrSrc [1:0] $end
$var reg 1 $ RUWr $end
$upscope $end
$scope module DM_inst $end
$var wire 32 F Address [31:0] $end
$var wire 3 G DMCtrl [2:0] $end
$var wire 1 , DMWr $end
$var wire 32 H DataWr [31:0] $end
$var reg 32 I DataRd [31:0] $end
$var reg 8 J data1 [7:0] $end
$var reg 8 K data2 [7:0] $end
$var reg 8 L data3 [7:0] $end
$var reg 8 M data4 [7:0] $end
$var reg 8 N out1 [7:0] $end
$var reg 8 O out2 [7:0] $end
$var reg 8 P out3 [7:0] $end
$var reg 8 Q out4 [7:0] $end
$scope begin $ivl_for_loop1 $end
$var integer 32 R i [31:0] $end
$upscope $end
$upscope $end
$scope module IM_inst $end
$var wire 32 S address [31:0] $end
$var reg 32 T instruction [31:0] $end
$var reg 8 U out1 [7:0] $end
$var reg 8 V out2 [7:0] $end
$var reg 8 W out3 [7:0] $end
$var reg 8 X out4 [7:0] $end
$upscope $end
$scope module IU_inst $end
$var wire 25 Y imm [24:0] $end
$var wire 3 Z src [2:0] $end
$var reg 32 [ ext [31:0] $end
$upscope $end
$scope module MuxPC_inst $end
$var wire 32 \ AluJump [31:0] $end
$var wire 1 ( NextPCSrc $end
$var wire 32 ] PC_4 [31:0] $end
$var reg 32 ^ NextPC [31:0] $end
$upscope $end
$scope module PC_inst $end
$var wire 32 _ PC_in [31:0] $end
$var wire 1 ! clk $end
$var reg 32 ` PC_out [31:0] $end
$upscope $end
$scope module RU_inst $end
$var wire 32 a DataWr [31:0] $end
$var wire 1 ! clk $end
$var wire 5 b rd [4:0] $end
$var wire 5 c rs1 [4:0] $end
$var wire 5 d rs2 [4:0] $end
$var wire 1 $ ruWr $end
$var wire 32 e ruRs2 [31:0] $end
$var wire 32 f ruRs1 [31:0] $end
$scope begin $ivl_for_loop0 $end
$var integer 32 g i [31:0] $end
$upscope $end
$upscope $end
$upscope $end
$upscope $end
$enddefinitions $end
$comment Show the parameter values. $end
$dumpall
$end
#0
$dumpvars
b100000 g
b0 f
b0 e
b1010 d
b0 c
b1000 b
b1010 a
b0 `
b100 _
b100 ^
b0 ]
b1010 \
b1010 [
b0 Z
b10100000000001000 Y
b10011 X
b100 W
b10100000 V
b0 U
b101000000000010000010011 T
b0 S
b100000 R
b0 Q
bx P
bx O
bx N
b0 M
b0 L
b0 K
b0 J
b0 I
b0 H
b0 G
b1010 F
b0 E
b0 D
b0 C
b0 B
b0 A
b10011 @
b0 ?
b0 >
b0 =
b0 <
b0 ;
b1010 :
b0 9
b1010 8
b0 7
b1010 6
b1010 5
b0 4
03
12
b0 1
b1010 0
b0 /
b0 .
b0 -
0,
b1010 +
b0 *
b101000000000010000010011 )
0(
b0 '
b100 &
b0 %
1$
b0 #
b0 "
1!
$end
#5
0!
#10
b101 6
b101 a
b101 0
b101 :
b101 F
b101 \
b101 5
b101 8
b1000 &
b1000 ^
b1000 _
b101 +
b101 [
b1010000000001001 Y
b1001 b
b101 d
b10100000000010010010011 )
b10100000000010010010011 T
b10010011 X
b1010000 V
b100 '
b100 S
b100 ]
b100 `
1!
#15
0!
#20
b0 6
b0 a
b0 0
b0 :
b0 F
b0 \
b0 5
b0 8
b1100 &
b1100 ^
b1100 _
b0 +
b0 [
02
b10010 Y
b10010 b
b0 d
b110011 @
b100100110011 )
b100100110011 T
b110011 X
b1001 W
b0 V
b1000 '
b1000 S
b1000 ]
b1000 `
1!
#25
0!
#30
b1010 6
b1010 a
b1010 0
b1010 :
b1010 F
b1010 \
b1010 4
b1010 7
b10000 &
b10000 ^
b10000 _
b1010 #
b1010 =
b1010 f
12
b100000001010 Y
b1010 b
b1000 c
b10011 @
b1000000010100010011 )
b1000000010100010011 T
b10011 X
b101 W
b100 V
b1100 '
b1100 S
b1100 ]
b1100 `
1!
#35
0!
#40
b101 6
b101 a
b101 0
b101 :
b101 F
b101 \
b101 4
b101 7
b10100 &
b10100 ^
b10100 _
b101 #
b101 =
b101 f
b100100001011 Y
b1011 b
b1001 c
b1001000010110010011 )
b1001000010110010011 T
b10010011 X
b10000101 W
b10000 '
b10000 S
b10000 ]
b10000 `
1!
#45
0!
#50
b1100 6
b1100 a
b1100 0
b1100 :
b1100 F
b1100 \
b1100 5
b1100 8
b0 4
b0 7
b1100 &
b1100 ^
b1100 _
1(
b1100 +
b1100 [
b0 #
b0 =
b0 f
0$
b11111 /
b11111 ;
b11111 B
b11000000000000001 Y
b1 b
b1100 d
b0 c
b1100111 @
b110000000000000011100111 )
b110000000000000011100111 T
b11100111 X
b0 W
b11000000 V
b10100 '
b10100 S
b10100 ]
b10100 `
1!
#55
0!
#60
b1010 6
b1010 a
b1010 0
b1010 :
b1010 F
b1010 \
b10000 &
b10000 ^
b10000 _
b0 5
b0 8
b1010 4
b1010 7
0(
b0 +
b0 [
b1010 #
b1010 =
b1010 f
1$
b0 /
b0 ;
b0 B
b100000001010 Y
b1010 b
b0 d
b1000 c
b10011 @
b1000000010100010011 )
b1000000010100010011 T
b10011 X
b101 W
b100 V
b1100 '
b1100 S
b1100 ]
b1100 `
1!
#65
0!
#70
b101 6
b101 a
b101 0
b101 :
b101 F
b101 \
b101 4
b101 7
b10100 &
b10100 ^
b10100 _
b101 #
b101 =
b101 f
b100100001011 Y
b1011 b
b1001 c
b1001000010110010011 )
b1001000010110010011 T
b10010011 X
b10000101 W
b10000 '
b10000 S
b10000 ]
b10000 `
1!
#75
0!
#80
b1100 6
b1100 a
b1100 0
b1100 :
b1100 F
b1100 \
b1100 5
b1100 8
b0 4
b0 7
b1100 &
b1100 ^
b1100 _
1(
b1100 +
b1100 [
b0 #
b0 =
b0 f
0$
b11111 /
b11111 ;
b11111 B
b11000000000000001 Y
b1 b
b1100 d
b0 c
b1100111 @
b110000000000000011100111 )
b110000000000000011100111 T
b11100111 X
b0 W
b11000000 V
b10100 '
b10100 S
b10100 ]
b10100 `
1!
#85
0!
#90
b1010 6
b1010 a
b1010 0
b1010 :
b1010 F
b1010 \
b10000 &
b10000 ^
b10000 _
b0 5
b0 8
b1010 4
b1010 7
0(
b0 +
b0 [
b1010 #
b1010 =
b1010 f
1$
b0 /
b0 ;
b0 B
b100000001010 Y
b1010 b
b0 d
b1000 c
b10011 @
b1000000010100010011 )
b1000000010100010011 T
b10011 X
b101 W
b100 V
b1100 '
b1100 S
b1100 ]
b1100 `
1!
#95
0!
#100
b101 6
b101 a
b101 0
b101 :
b101 F
b101 \
b101 4
b101 7
b10100 &
b10100 ^
b10100 _
b101 #
b101 =
b101 f
b100100001011 Y
b1011 b
b1001 c
b1001000010110010011 )
b1001000010110010011 T
b10010011 X
b10000101 W
b10000 '
b10000 S
b10000 ]
b10000 `
1!
#105
0!
#110
b1100 6
b1100 a
b1100 0
b1100 :
b1100 F
b1100 \
b1100 5
b1100 8
b0 4
b0 7
b1100 &
b1100 ^
b1100 _
1(
b1100 +
b1100 [
b0 #
b0 =
b0 f
0$
b11111 /
b11111 ;
b11111 B
b11000000000000001 Y
b1 b
b1100 d
b0 c
b1100111 @
b110000000000000011100111 )
b110000000000000011100111 T
b11100111 X
b0 W
b11000000 V
b10100 '
b10100 S
b10100 ]
b10100 `
1!
#115
0!
#120
b1010 6
b1010 a
b1010 0
b1010 :
b1010 F
b1010 \
b10000 &
b10000 ^
b10000 _
b0 5
b0 8
b1010 4
b1010 7
0(
b0 +
b0 [
b1010 #
b1010 =
b1010 f
1$
b0 /
b0 ;
b0 B
b100000001010 Y
b1010 b
b0 d
b1000 c
b10011 @
b1000000010100010011 )
b1000000010100010011 T
b10011 X
b101 W
b100 V
b1100 '
b1100 S
b1100 ]
b1100 `
1!
#125
0!
#130
b101 6
b101 a
b101 0
b101 :
b101 F
b101 \
b101 4
b101 7
b10100 &
b10100 ^
b10100 _
b101 #
b101 =
b101 f
b100100001011 Y
b1011 b
b1001 c
b1001000010110010011 )
b1001000010110010011 T
b10010011 X
b10000101 W
b10000 '
b10000 S
b10000 ]
b10000 `
1!
#135
0!
#140
b1100 6
b1100 a
b1100 0
b1100 :
b1100 F
b1100 \
b1100 5
b1100 8
b0 4
b0 7
b1100 &
b1100 ^
b1100 _
1(
b1100 +
b1100 [
b0 #
b0 =
b0 f
0$
b11111 /
b11111 ;
b11111 B
b11000000000000001 Y
b1 b
b1100 d
b0 c
b1100111 @
b110000000000000011100111 )
b110000000000000011100111 T
b11100111 X
b0 W
b11000000 V
b10100 '
b10100 S
b10100 ]
b10100 `
1!
#145
0!
#150
b1010 6
b1010 a
b1010 0
b1010 :
b1010 F
b1010 \
b10000 &
b10000 ^
b10000 _
b0 5
b0 8
b1010 4
b1010 7
0(
b0 +
b0 [
b1010 #
b1010 =
b1010 f
1$
b0 /
b0 ;
b0 B
b100000001010 Y
b1010 b
b0 d
b1000 c
b10011 @
b1000000010100010011 )
b1000000010100010011 T
b10011 X
b101 W
b100 V
b1100 '
b1100 S
b1100 ]
b1100 `
1!
#155
0!
#160
b101 6
b101 a
b101 0
b101 :
b101 F
b101 \
b101 4
b101 7
b10100 &
b10100 ^
b10100 _
b101 #
b101 =
b101 f
b100100001011 Y
b1011 b
b1001 c
b1001000010110010011 )
b1001000010110010011 T
b10010011 X
b10000101 W
b10000 '
b10000 S
b10000 ]
b10000 `
1!
#165
0!
#170
b1100 6
b1100 a
b1100 0
b1100 :
b1100 F
b1100 \
b1100 5
b1100 8
b0 4
b0 7
b1100 &
b1100 ^
b1100 _
1(
b1100 +
b1100 [
b0 #
b0 =
b0 f
0$
b11111 /
b11111 ;
b11111 B
b11000000000000001 Y
b1 b
b1100 d
b0 c
b1100111 @
b110000000000000011100111 )
b110000000000000011100111 T
b11100111 X
b0 W
b11000000 V
b10100 '
b10100 S
b10100 ]
b10100 `
1!
#175
0!
#180
b1010 6
b1010 a
b1010 0
b1010 :
b1010 F
b1010 \
b10000 &
b10000 ^
b10000 _
b0 5
b0 8
b1010 4
b1010 7
0(
b0 +
b0 [
b1010 #
b1010 =
b1010 f
1$
b0 /
b0 ;
b0 B
b100000001010 Y
b1010 b
b0 d
b1000 c
b10011 @
b1000000010100010011 )
b1000000010100010011 T
b10011 X
b101 W
b100 V
b1100 '
b1100 S
b1100 ]
b1100 `
1!
#185
0!
#190
b101 6
b101 a
b101 0
b101 :
b101 F
b101 \
b101 4
b101 7
b10100 &
b10100 ^
b10100 _
b101 #
b101 =
b101 f
b100100001011 Y
b1011 b
b1001 c
b1001000010110010011 )
b1001000010110010011 T
b10010011 X
b10000101 W
b10000 '
b10000 S
b10000 ]
b10000 `
1!
#195
0!
#200
b1100 6
b1100 a
b1100 0
b1100 :
b1100 F
b1100 \
b1100 5
b1100 8
b0 4
b0 7
b1100 &
b1100 ^
b1100 _
1(
b1100 +
b1100 [
b0 #
b0 =
b0 f
0$
b11111 /
b11111 ;
b11111 B
b11000000000000001 Y
b1 b
b1100 d
b0 c
b1100111 @
b110000000000000011100111 )
b110000000000000011100111 T
b11100111 X
b0 W
b11000000 V
b10100 '
b10100 S
b10100 ]
b10100 `
1!
