CU/CU.sv
module CU(
        input [6:0] Opcode,
        input [2:0] Function3,
        input [6:0] Function7,
        output logic [2:0] ImmSrc = 3'b000,
        output logic ALUASrc = 0,
        output logic ALUBSrc = 0,
        output logic RUWr = 0,
        output logic [4:0] BrOp = 5'b00000,
        output logic [3:0] ALUOp = 4'b0000,
        output logic DMWr = 0,
        output logic [2:0] DMCtrl = 3'b000,
        output logic [1:0] RUDataWrSrc = 2'b00
    );

    always @(*) begin
        case(Opcode)
            7'b0110011: begin //Tipo R
                ImmSrc = 3'b000; 
                BrOp = 5'b00000; 
                DMWr = 1'b0; 
                DMCtrl = 3'b000; 
                RUWr = 1'b1; 
                ALUASrc = 1'b0; 
                ALUBSrc = 1'b0; 
                ALUOp = {Function7[5], Function3[2:0]};
                RUDataWrSrc = 2'b00;    
            end
            7'b0010011: begin //Tipo I
                ImmSrc = 3'b000;
                BrOp = 5'b00000;
                DMWr = 1'b0;
                DMCtrl = 3'b000;
                RUWr = 1'b1; 
                ALUASrc = 1'b0;
                ALUBSrc = 1'b1;
                if (Function3 == 3'b101 || 3'b001) begin
                    ALUOp = {Function7[5], Function3[2:0]};
                end else begin
                    ALUOp = {1'b0,Function3[2:0]};
                end
                RUDataWrSrc = 2'b00;
            end
            7'b1100011: begin //Tipo B
                ImmSrc = 3'b101;  
                BrOp = {2'b01, Function3[2:0]};
                DMWr = 1'b0;
                DMCtrl = 3'b000;
                RUWr = 1'b0;
                ALUASrc = 1'b1;
                ALUBSrc = 1'b1;
                ALUOp = 4'b0000;
                RUDataWrSrc = 2'b00;
            end
            7'b0100011: begin //Tipo S
                ImmSrc = 3'b001;  
                BrOp = 5'b00000;
                DMWr = 1'b1;
                DMCtrl = Function3[2:0];
                RUWr = 1'b0;
                ALUASrc = 1'b0;
                ALUBSrc = 1'b1;
                ALUOp = 4'b0000;
                RUDataWrSrc = 2'b00;
            end 
            7'b0000011: begin //Tipo I - Load
                ImmSrc = 3'b000;  
                BrOp = 5'b00000;
                DMWr = 1'b0;
                DMCtrl = Function3[2:0];
                RUWr = 1'b1;
                ALUASrc = 1'b0;
                ALUBSrc = 1'b1;
                ALUOp = 4'b0000;
                RUDataWrSrc = 2'b01;
            end
            7'b1100111: begin //Tipo I - Jalr
                ImmSrc = 3'b000;  
                BrOp = 5'b11111;
                DMWr = 1'b0;
                DMCtrl = 3'b000;
                RUWr = 1'b0;
                ALUASrc = 1'b0;
                ALUBSrc = 1'b1;
                ALUOp = 4'b0000;
                RUDataWrSrc = 2'b00;
            end  
            7'b1101111: begin //Tipo J
                ImmSrc = 3'b110;  
                BrOp = 5'b11111;
                DMWr = 1'b0;
                DMCtrl = 3'b000;
                RUWr = 1'b1;
                ALUASrc = 1'b1;
                ALUBSrc = 1'b1;
                ALUOp = 4'b0000;
                RUDataWrSrc = 2'b10;
            end 
            7'b0110111: begin //Tipo U - lui
                ImmSrc = 3'b010;  
                BrOp = 5'b00000;
                DMWr = 1'b0;
                DMCtrl = 3'b000;
                RUWr = 1'b1;
                ALUASrc = 1'b0;
                ALUBSrc = 1'b1;
                ALUOp = 4'b0000;
                RUDataWrSrc = 2'b00;
            end 
            7'b0010111: begin //Tipo U - auipc
                ImmSrc = 3'b010;  
                BrOp = 5'b00000;
                DMWr = 1'b0;
                DMCtrl = 3'b000;
                RUWr = 1'b1;
                ALUASrc = 1'b1;
                ALUBSrc = 1'b1;
                ALUOp = 4'b0000;
                RUDataWrSrc = 2'b00;
            end 

        default BrOp = 5'b00000;

        endcase
    end
endmodule

CU/CU_Tb.sv
module CU_Tb;
    reg [6:0] Opcode_tb;
    reg [2:0] Function3_tb;
    reg [6:0] Function7_tb;
    wire [2:0] ImmSrc_tb;
    wire ALUASrc_tb;
    wire ALUBSrc_tb;
    wire RUWr_tb;
    wire [4:0] BrOp_tb;
    wire [3:0] ALUOp_tb;
    wire DMWr_tb;
    wire [2:0] DMCtrl_tb;
    wire [1:0] RUDataWrSrc_tb;

    CU CU_inst(
        .Opcode(Opcode_tb),
        .Function3(Function3_tb),
        .Function7(Function7_tb),
        .ImmSrc(ImmSrc_tb),
        .ALUASrc(ALUASrc_tb),
        .ALUBSrc(ALUBSrc_tb),
        .RUWr(RUWr_tb),
        .BrOp(BrOp_tb),
        .ALUOp(ALUOp_tb),
        .DMWr(DMWr_tb),
        .DMCtrl(DMCtrl_tb),
        .RUDataWrSrc(RUDataWrSrc_tb)
    );

    initial begin
        $dumpfile("CU_tb.vcd");
        $dumpvars(0, CU_Tb);

        //Tipo R
        Opcode_tb = 7'b0110011;
        Function3_tb = 3'b000;
        Function7_tb = 7'b0100000;
        #10;

        //Tipo I
        Opcode_tb = 7'b0010011;
        #10;

        //Tipo B
        Opcode_tb = 7'b1100011;
        #10;

        //Tipo S
        Opcode_tb = 7'b0100011;
        #10;

        //Tipo I - Load
        Opcode_tb = 7'b0000011;
        #10;

        //Tipo I - Jalr
        Opcode_tb = 7'b1100111;
        #10;

        //Tipo J
        Opcode_tb = 7'b1101111;
        #10;

        //Tipo U - lui
        Opcode_tb = 7'b0110111;
        #10;

        //Tipo U - auipc
        Opcode_tb = 7'b0010111;
        #10;    
    end

endmodule

CU/CU_tb.vcd
$date
	Thu Apr 25 22:25:21 2024
$end
$version
	Icarus Verilog
$end
$timescale
	1s
$end
$scope module CU_Tb $end
$var wire 1 ! RUWr_tb $end
$var wire 2 " RUDataWrSrc_tb [1:0] $end
$var wire 3 # ImmSrc_tb [2:0] $end
$var wire 1 $ DMWr_tb $end
$var wire 3 % DMCtrl_tb [2:0] $end
$var wire 5 & BrOp_tb [4:0] $end
$var wire 4 ' ALUOp_tb [3:0] $end
$var wire 1 ( ALUBSrc_tb $end
$var wire 1 ) ALUASrc_tb $end
$var reg 3 * Function3_tb [2:0] $end
$var reg 7 + Function7_tb [6:0] $end
$var reg 7 , Opcode_tb [6:0] $end
$scope module CU_inst $end
$var wire 3 - Function3 [2:0] $end
$var wire 7 . Function7 [6:0] $end
$var wire 7 / Opcode [6:0] $end
$var reg 1 ) ALUASrc $end
$var reg 1 ( ALUBSrc $end
$var reg 4 0 ALUOp [3:0] $end
$var reg 5 1 BrOp [4:0] $end
$var reg 3 2 DMCtrl [2:0] $end
$var reg 1 $ DMWr $end
$var reg 3 3 ImmSrc [2:0] $end
$var reg 2 4 RUDataWrSrc [1:0] $end
$var reg 1 ! RUWr $end
$upscope $end
$upscope $end
$enddefinitions $end
$comment Show the parameter values. $end
$dumpall
$end
#0
$dumpvars
b0 4
b0 3
b0 2
b0 1
b1000 0
b110011 /
b100000 .
b0 -
b110011 ,
b100000 +
b0 *
0)
0(
b1000 '
b0 &
b0 %
0$
b0 #
b0 "
1!
$end
#10
1(
b10011 ,
b10011 /
#20
b0 '
b0 0
1)
0!
b1000 &
b1000 1
b101 #
b101 3
b1100011 ,
b1100011 /
#30
0)
1$
b0 &
b0 1
b1 #
b1 3
b100011 ,
b100011 /
#40
b1 "
b1 4
1!
0$
b0 #
b0 3
b11 ,
b11 /
#50
b0 "
b0 4
0!
b11111 &
b11111 1
b1100111 ,
b1100111 /
#60
b10 "
b10 4
1)
1!
b110 #
b110 3
b1101111 ,
b1101111 /
#70
b0 "
b0 4
0)
b0 &
b0 1
b10 #
b10 3
b110111 ,
b110111 /
#80
1)
b10111 ,
b10111 /
