BU/BU.sv
module BU(
        input logic [31:0] A,
        input logic [31:0] B,
        input logic [4:0] BrOp,
        output reg NextPCSrc
    );

    always @(*)
        case(BrOp)
            5'b00000 : NextPCSrc = 0;
            5'b11111 : NextPCSrc = 1;
            5'b01000 : NextPCSrc = (A == B);
            5'b01001 : NextPCSrc = (A != B);
            5'b01100 : NextPCSrc = ($signed(A) < $signed(B));
            5'b01101 : NextPCSrc = ($signed(A) >= $signed(B));
            5'b01110 : NextPCSrc = (A < B);
            5'b01111 : NextPCSrc = (A >= B);

            default NextPCSrc = 0;
        endcase
    
endmodule

BU/BU_Tb.sv
module BU_Tb();
    reg [31:0] A_tb;
    reg [31:0] B_tb;
    reg [4:0] BrOp_tb;
    wire NextPCSrc_tb;

    BU BU_inst(
        .A(A_tb),
        .B(B_tb),
        .BrOp(BrOp_tb),
        .NextPCSrc(NextPCSrc_tb)
    );

    initial begin 
        $dumpfile("dump.vcd");
        $dumpvars;

        A_tb = 32'h00000005;
        B_tb = 32'h00000007;

        BrOp_tb = 5'b00000;
        #10;

        BrOp_tb = 5'b01000;
        #10;

        BrOp_tb = 5'b01001;
        #10;

        BrOp_tb = 5'b01100;
        #10;

        BrOp_tb = 5'b01101;
        #10;

        A_tb = -32'h00000005;
        BrOp_tb = 5'b01110;
        #10;

        A_tb = -32'h00000005;
        BrOp_tb = 5'b01111;
        #10;

        A_tb = 32'h00000005;
        BrOp_tb = 5'b11111;
        #10;

        $finish;
    end
endmodule

BU/dump.vcd
$date
	Fri Apr 26 20:32:21 2024
$end
$version
	Icarus Verilog
$end
$timescale
	1s
$end
$scope module BU_Tb $end
$var wire 1 ! NextPCSrc_tb $end
$var reg 32 " A_tb [31:0] $end
$var reg 32 # B_tb [31:0] $end
$var reg 5 $ BrOp_tb [4:0] $end
$scope module BU_inst $end
$var wire 32 % A [31:0] $end
$var wire 32 & B [31:0] $end
$var wire 5 ' BrOp [4:0] $end
$var reg 1 ! NextPCSrc $end
$upscope $end
$upscope $end
$enddefinitions $end
$comment Show the parameter values. $end
$dumpall
$end
#0
$dumpvars
b0 '
b111 &
b101 %
b0 $
b111 #
b101 "
0!
$end
#10
b1000 $
b1000 '
#20
1!
b1001 $
b1001 '
#30
b1100 $
b1100 '
#40
0!
b1101 $
b1101 '
#50
b1110 $
b1110 '
b11111111111111111111111111111011 "
b11111111111111111111111111111011 %
#60
1!
b1111 $
b1111 '
#70
b11111 $
b11111 '
b101 "
b101 %
