DM/DM.sv
module DM(
        input [31:0] Address,
        input [31:0] DataWr,
        input DMWr,
        input [2:0] DMCtrl,
        output reg [31:0] DataRd
    );

    logic [7:0] data_mem [31:0];
    logic [7:0] data1, data2, data3, data4;
    logic [7:0] out1, out2, out3, out4;

    initial begin
        for (int i = 0; i < 32; i++) begin
            data_mem[i] = 8'b0;
        end
    end

    always @(*) begin
       data1 = DataWr[31:24];
       data2 = DataWr[23:16];
       data3 = DataWr[15:8];
       data4 = DataWr[7:0];

        if (DMWr == 1) begin
            case (DMCtrl)
                3'b000 :
                    begin 
                        data_mem[Address] = data4;
                        data_mem[Address + 1] = 8'b0;
                        data_mem[Address + 2] = 8'b0;
                        data_mem[Address + 3] = 8'b0;
                    end
                3'b001 : 
                    begin 
                        data_mem[Address] = data4;
                        data_mem[Address + 1] = data3;
                        data_mem[Address + 2] = 8'b0;
                        data_mem[Address + 3] = 8'b0;
                    end
                3'b010 : 
                    begin
                        data_mem[Address] = data4;
                        data_mem[Address + 1] = data3;
                        data_mem[Address + 2] = data2;
                        data_mem[Address + 3] = data1;
                    end 
            endcase
        end
        else begin 
            case (DMCtrl)
                3'b000 : 
                    begin
                        out4 = data_mem[Address];
                        DataRd = {{24{out4[7]}}, out4};
                    end 
                3'b001:
                    begin
                        out4 = data_mem[Address];
                        out3 = data_mem[Address + 1];
                        DataRd = {{16{out3[7]}}, out3, out4};
                    end 
                3'b010:
                    begin
                        out4 = data_mem[Address];
                        out3 = data_mem[Address + 1];
                        out2 = data_mem[Address + 2];
                        out1 = data_mem[Address + 3];
                        DataRd = {out1, out2, out3, out4};
                    end 
                3'b100 :
                    begin
                        out4 = data_mem[Address];
                        DataRd = {{24{1'b0}}, out4};
                    end 
                3'b101 :
                    begin
                        out4 = data_mem[Address];
                        out3 = data_mem[Address + 1];
                        DataRd = {{16{1'b0}}, out3, out4};
                    end 
            endcase
        end
    end
endmodule

DM/DM_Tb.sv
module DM_Tb;
    reg [31:0] Address_tb;
    reg [31:0] DataWr_tb;
    reg DMWr_tb;
    reg [2:0] DMCtrl_tb;
    wire [31:0] DataRd_tb;

    DM DM_inst (
        .Address(Address_tb),
        .DataWr(DataWr_tb),
        .DMWr(DMWr_tb),
        .DMCtrl(DMCtrl_tb),
        .DataRd(DataRd_tb)
    );

    always #5 DMWr_tb = ~DMWr_tb;

    initial begin
        $dumpfile("DM_tb.vcd");
        $dumpvars(0, DM_Tb);

        DMWr_tb = 1;
        DMCtrl_tb = 3'b010;
        DataWr_tb = 32'b01010101010101010101010101010101;
        Address_tb = 32'b0;
        #10;
        
        DataWr_tb = 32'b00000000000000000000000000000001;
        Address_tb = 4;
        #10;

        DataWr_tb = 32'b00000000000111111111110000001111;
        Address_tb = 8;
        #10;

        DataWr_tb = 32'b01010101011101010101010101111111;
        Address_tb = 12;
        #10;

        DataWr_tb = 32'b01010101111111111101010101010101;
        Address_tb = 16;
        #10;

        DataWr_tb = 32'b10101010101011111111000010101010;
        Address_tb = 20;
        #10;

        DataWr_tb = 32'b01010111111000010101010101010101;
        Address_tb = 24;
        #10;

        DataWr_tb = 32'b01011111100000110101010101010101;
        Address_tb = 28;
        #10;
        $finish;
    end
endmodule

DM/DM_tb.vcd
$date
	Mon Apr 29 18:29:59 2024
$end
$version
	Icarus Verilog
$end
$timescale
	1s
$end
$scope module DM_Tb $end
$var wire 32 ! DataRd_tb [31:0] $end
$var reg 32 " Address_tb [31:0] $end
$var reg 3 # DMCtrl_tb [2:0] $end
$var reg 1 $ DMWr_tb $end
$var reg 32 % DataWr_tb [31:0] $end
$scope module DM_inst $end
$var wire 32 & Address [31:0] $end
$var wire 3 ' DMCtrl [2:0] $end
$var wire 1 $ DMWr $end
$var wire 32 ( DataWr [31:0] $end
$var reg 32 ) DataRd [31:0] $end
$var reg 8 * data1 [7:0] $end
$var reg 8 + data2 [7:0] $end
$var reg 8 , data3 [7:0] $end
$var reg 8 - data4 [7:0] $end
$var reg 8 . out1 [7:0] $end
$var reg 8 / out2 [7:0] $end
$var reg 8 0 out3 [7:0] $end
$var reg 8 1 out4 [7:0] $end
$scope begin $ivl_for_loop0 $end
$var integer 32 2 i [31:0] $end
$upscope $end
$upscope $end
$upscope $end
$enddefinitions $end
$comment Show the parameter values. $end
$dumpall
$end
#0
$dumpvars
b100000 2
bx 1
bx 0
bx /
bx .
b1010101 -
b1010101 ,
b1010101 +
b1010101 *
bx )
b1010101010101010101010101010101 (
b10 '
b0 &
b1010101010101010101010101010101 %
1$
b10 #
b0 "
bx !
$end
#5
b1010101010101010101010101010101 !
b1010101010101010101010101010101 )
b1010101 .
b1010101 /
b1010101 0
b1010101 1
0$
#10
b1 -
b0 ,
b0 +
b0 *
1$
b100 "
b100 &
b1 %
b1 (
#15
b1 !
b1 )
b0 .
b0 /
b0 0
b1 1
0$
#20
b1111 -
b11111100 ,
b11111 +
1$
b1000 "
b1000 &
b111111111110000001111 %
b111111111110000001111 (
#25
b111111111110000001111 !
b111111111110000001111 )
b11111 /
b11111100 0
b1111 1
0$
#30
b1111111 -
b1010101 ,
b1110101 +
b1010101 *
1$
b1100 "
b1100 &
b1010101011101010101010101111111 %
b1010101011101010101010101111111 (
#35
b1010101011101010101010101111111 !
b1010101011101010101010101111111 )
b1010101 .
b1110101 /
b1010101 0
b1111111 1
0$
#40
b1010101 -
b11010101 ,
b11111111 +
1$
b10000 "
b10000 &
b1010101111111111101010101010101 %
b1010101111111111101010101010101 (
#45
b1010101111111111101010101010101 !
b1010101111111111101010101010101 )
b11111111 /
b11010101 0
b1010101 1
0$
#50
b10101010 -
b11110000 ,
b10101111 +
b10101010 *
1$
b10100 "
b10100 &
b10101010101011111111000010101010 %
b10101010101011111111000010101010 (
#55
b10101010101011111111000010101010 !
b10101010101011111111000010101010 )
b10101010 .
b10101111 /
b11110000 0
b10101010 1
0$
#60
b1010101 -
b1010101 ,
b11100001 +
b1010111 *
1$
b11000 "
b11000 &
b1010111111000010101010101010101 %
b1010111111000010101010101010101 (
#65
b1010111111000010101010101010101 !
b1010111111000010101010101010101 )
b1010111 .
b11100001 /
b1010101 0
b1010101 1
0$
#70
b10000011 +
b1011111 *
1$
b11100 "
b11100 &
b1011111100000110101010101010101 %
b1011111100000110101010101010101 (
#75
b1011111100000110101010101010101 !
b1011111100000110101010101010101 )
b1011111 .
b10000011 /
0$
#80
1$
