ALU/ALU.sv
module ALU(
    input [31:0] A,
    input [31:0] B,
    input [3:0] ALUop,
    output reg [31:0] ALUS
    );

    always @(*)
      
    begin
        case(ALUop)
            4'b0000: ALUS = A + B; // Suma
            4'b1000: ALUS = A - B; // Resta
            4'b0111: ALUS = A & B; // AND
            4'b0110: ALUS = A | B; // OR
            4'b0100: ALUS = A ^ B; // XOR
            4'b0001: ALUS = A << B; // Corrimiento lógico izquierdo.
            4'b0101: ALUS = A >> B; // Corrimiento lógico derecho.
            4'b1101: ALUS = A >>> B; // Corrimiento aritmético a la derecha.
            4'b0010: ALUS = ($signed(A) < $signed(B)); // Menor que B (con signo)
            4'b0011: ALUS = A < B; // Menor que B (sin signo)
            default: ALUS = 32'b0; // Default en caso de ALUop desconocido
        endcase
    end
endmodule

ALU/ALU_Tb.sv
module ALU_Tb();
  reg [31:0] A_tb, B_tb;
  reg [3:0] ALUop_tb; 
  wire [31:0] ALUs_tb;

  ALU ALU_inst (
    .A(A_tb),
    .B(B_tb),
    .ALUop(ALUop_tb),
    .ALUS(ALUs_tb)
  );
  
  initial begin 
    $dumpfile("dump.vcd");
    $dumpvars;

    //Suma
    A_tb = 32'h00000005;
    B_tb = 32'h00000007;
    ALUop_tb = 4'b0000;
    
    #10;

    //Resta
    A_tb = 32'h00000005;
    B_tb = 32'h00000007;
    ALUop_tb = 4'b1000;
    
    #10;

    //AND
    A_tb = 32'h00000005;
    B_tb = 32'h00000007;
    ALUop_tb = 4'b0111;
    
    #10;

    //OR
    A_tb = 32'h00000005;
    B_tb = 32'h00000007;
    ALUop_tb = 4'b0110;
    
    #10;

    //XOR
    A_tb = 32'h00000005;
    B_tb = 32'h00000007;
    ALUop_tb = 4'b0100;
    
    #10;

    //Corrimiento lógico izquierdo.
    A_tb = 32'h00000005;
    ALUop_tb = 4'b0001;
    
    #10;

    //Corrimiento lógico derecho.
    A_tb = 32'h00000005;
    ALUop_tb = 4'b0101;
    
    #10;

    //Corrimiento aritmético a la derecha.
    A_tb = 32'h00000005;
    ALUop_tb = 4'b1101;
    
    #10;

    // Menor que B (con signo)
    A_tb = -32'h00000005;
    B_tb = 32'h00000005;
    ALUop_tb = 4'b0010;
    
    #10;

    // Menor que B (Sin signo)
    A_tb = -32'h00000005;
    B_tb = 32'h00000005;
    ALUop_tb = 4'b0011;

    #10;

    $finish;
  end
endmodule

ALU/dump.vcd
$date
	Fri Apr 26 15:38:54 2024
$end
$version
	Icarus Verilog
$end
$timescale
	1s
$end
$scope module ALU_Tb $end
$var wire 32 ! ALUs_tb [31:0] $end
$var reg 4 " ALUop_tb [3:0] $end
$var reg 32 # A_tb [31:0] $end
$var reg 32 $ B_tb [31:0] $end
$scope module ALU_inst $end
$var wire 32 % A [31:0] $end
$var wire 4 & ALUop [3:0] $end
$var wire 32 ' B [31:0] $end
$var reg 32 ( ALUS [31:0] $end
$upscope $end
$upscope $end
$enddefinitions $end
$comment Show the parameter values. $end
$dumpall
$end
#0
$dumpvars
b1100 (
b111 '
b0 &
b101 %
b111 $
b101 #
b0 "
b1100 !
$end
#10
b11111111111111111111111111111110 !
b11111111111111111111111111111110 (
b1000 "
b1000 &
#20
b101 !
b101 (
b111 "
b111 &
#30
b111 !
b111 (
b110 "
b110 &
#40
b10 !
b10 (
b100 "
b100 &
#50
b1010000000 !
b1010000000 (
b1 "
b1 &
#60
b0 !
b0 (
b101 "
b101 &
#70
b1101 "
b1101 &
#80
b1 !
b1 (
b10 "
b10 &
b101 $
b101 '
b11111111111111111111111111111011 #
b11111111111111111111111111111011 %
#90
b0 !
b0 (
b11 "
b11 &
