RU/RU.sv
module RU (
  input logic clk,
  input logic ruWr,
  input logic [4:0] rs1,
  input logic [4:0] rs2,
  input logic [4:0] rd,
  input logic [31:0] DataWr,
  output logic [31:0] ruRs1,
  output logic [31:0] ruRs2
);

  logic [31:0] registers [0:31];

  initial begin
    for (int i = 0; i < 32; i++) begin
      registers[i] = 0;
    registers[2] = 5'b11111;
    end
  end

  assign ruRs1 = (rs1 == 0) ? 0 : registers[rs1];
  assign ruRs2 = (rs2 == 0) ? 0 : registers[rs2];

  always_ff @(posedge clk) begin
    if ((ruWr == 1) && (rd != 0))
      registers[rd] <= DataWr;
  end

endmodule

RU/RU_Tb.sv
module RU_Tb;
    logic clk_tb;
    logic ruWr_tb;
    logic [4:0] rs1_tb;
    logic [4:0] rs2_tb;
    logic [4:0] rd_tb;
    logic [31:0] DataWr_tb;
    logic [31:0] ruRs1_tb;
    logic [31:0] ruRs2_tb;

    RU RU_inst(
        .clk(clk_tb),
        .ruWr(ruWr_tb),
        .rs1(rs1_tb),
        .rs2(rs2_tb),
        .rd(rd_tb),
        .DataWr(DataWr_tb),
        .ruRs1(ruRs1_tb),
        .ruRs2(ruRs2_tb)
    );
    
    always #5 clk_tb = ~clk_tb; 

    initial begin
        $dumpfile("RU_tb.vcd");
        $dumpvars(0, RU_Tb);

        clk_tb = 0;
        ruWr_tb = 1;
        rs2_tb = 5'b01000;

        rd_tb = 5'b01010;
        DataWr_tb = 32'b01100111011001110110011101100111;
        rs1_tb = 5'b01010;
        #10;

        rd_tb = 5'b01000;
        DataWr_tb = 32'b01100111011001110110011101100000;
        rs1_tb = 5'b01000;
        #10;

        rd_tb = 5'b01001;
        DataWr_tb = 32'b01100111011000000110011101100111;
        rs1_tb = 5'b01001;
        #10;

        rd_tb = 5'b01011;
        DataWr_tb = 32'b01100111011011000110011111100111;
        rs1_tb = 5'b01011;
        #10;

        $finish;
    end

endmodule

RU/RU_tb.vcd
$date
	Thu Apr 25 22:35:07 2024
$end
$version
	Icarus Verilog
$end
$timescale
	1s
$end
$scope module RU_Tb $end
$var wire 32 ! ruRs2_tb [31:0] $end
$var wire 32 " ruRs1_tb [31:0] $end
$var reg 32 # DataWr_tb [31:0] $end
$var reg 1 $ clk_tb $end
$var reg 5 % rd_tb [4:0] $end
$var reg 5 & rs1_tb [4:0] $end
$var reg 5 ' rs2_tb [4:0] $end
$var reg 1 ( ruWr_tb $end
$scope module RU_inst $end
$var wire 32 ) DataWr [31:0] $end
$var wire 1 $ clk $end
$var wire 5 * rd [4:0] $end
$var wire 5 + rs1 [4:0] $end
$var wire 5 , rs2 [4:0] $end
$var wire 1 ( ruWr $end
$var wire 32 - ruRs2 [31:0] $end
$var wire 32 . ruRs1 [31:0] $end
$scope begin $ivl_for_loop0 $end
$var integer 32 / i [31:0] $end
$upscope $end
$upscope $end
$upscope $end
$enddefinitions $end
$comment Show the parameter values. $end
$dumpall
$end
#0
$dumpvars
b100000 /
b0 .
b0 -
b1000 ,
b1010 +
b1010 *
b1100111011001110110011101100111 )
1(
b1000 '
b1010 &
b1010 %
0$
b1100111011001110110011101100111 #
b0 "
b0 !
$end
#5
b1100111011001110110011101100111 "
b1100111011001110110011101100111 .
1$
#10
b0 "
b0 .
0$
b1000 &
b1000 +
b1100111011001110110011101100000 #
b1100111011001110110011101100000 )
b1000 %
b1000 *
#15
b1100111011001110110011101100000 "
b1100111011001110110011101100000 .
b1100111011001110110011101100000 !
b1100111011001110110011101100000 -
1$
#20
b0 "
b0 .
0$
b1001 &
b1001 +
b1100111011000000110011101100111 #
b1100111011000000110011101100111 )
b1001 %
b1001 *
#25
b1100111011000000110011101100111 "
b1100111011000000110011101100111 .
1$
#30
b0 "
b0 .
0$
b1011 &
b1011 +
b1100111011011000110011111100111 #
b1100111011011000110011111100111 )
b1011 %
b1011 *
#35
b1100111011011000110011111100111 "
b1100111011011000110011111100111 .
1$
